envrun/__init__.py
envrun/default_backends.py
envrun/interfaces.py
envrun/utils.py
envrun-0.0.5.dist-info/LICENSE
envrun-0.0.5.dist-info/METADATA
envrun-0.0.5.dist-info/WHEEL
envrun-0.0.5.dist-info/entry_points.txt
envrun-0.0.5.dist-info/top_level.txt
envrun-0.0.5.dist-info/RECORD
