Metadata-Version: 2.1
Name: envrun
Version: 0.0.5
Summary: Run a command with dynamically-sourced environment variables.
Home-page: https://github.com/JanLikar/envrun
Author: Jan Likar
Author-email: jan.likar@protonmail.com
License: UNKNOWN
Keywords: cli util secret-managament
Platform: UNKNOWN
Classifier: Programming Language :: Python
Classifier: Development Status :: 4 - Beta
Classifier: Environment :: Console
Classifier: Intended Audience :: Developers
Classifier: Intended Audience :: System Administrators
Classifier: License :: OSI Approved :: MIT License
Classifier: Topic :: Security
Classifier: Topic :: Utilities
Requires-Python: >=3.6
Requires-Dist: click
Requires-Dist: toml
Requires-Dist: SecretStorage
Provides-Extra: dev
Requires-Dist: black ; extra == 'dev'
Requires-Dist: pip-tools ; extra == 'dev'
Requires-Dist: pdbpp ; extra == 'dev'
